numerosPrimos/__init__.py
generarPrimos-1.0.dist-info/LICENSE.txt
generarPrimos-1.0.dist-info/METADATA
generarPrimos-1.0.dist-info/WHEEL
generarPrimos-1.0.dist-info/top_level.txt
generarPrimos-1.0.dist-info/RECORD
