Metadata-Version: 2.1
Name: generarPrimos
Version: 1.0
Summary: Herramienta para generar números primos
Home-page: UNKNOWN
Author: Enrique A.R
Author-email: UNKNOWN
License: GNU/GPL
Keywords: primos,matemáticas,operaciones elementales
Platform: UNKNOWN
Classifier: Development Status :: 3 - Alpha
Classifier: Intended Audience :: Developers
Classifier: Topic :: Utilities
Classifier: License :: OSI Approved :: GNU General Public License v3 (GPLv3)
Classifier: Programming Language :: Python :: 3
Classifier: Operating System :: OS Independent
